sltx-0.1.73.data/scripts/sltx
sltx-0.1.73.data/scripts/sltxc
sltx-0.1.73.data/scripts/sltxrc
sltxpkg/__init__.py
sltxpkg/cmd_line_args.py
sltxpkg/command_config.py
sltxpkg/commands.py
sltxpkg/config.py
sltxpkg/dep.py
sltxpkg/generate.py
sltxpkg/globals.py
sltxpkg/heart.py
sltxpkg/log_control.py
sltxpkg/prompt.py
sltxpkg/types.py
sltxpkg/util.py
sltxpkg/data/__init__.py
sltxpkg/data/sltx-dep.yaml
sltxpkg/data/version.info
sltxpkg/data/latexmk/__init__.py
sltxpkg/data/latexmk/configs/__init__.py
sltxpkg/data/latexmk/configs/glossary.mkrc
sltxpkg/data/latexmk/configs/index.mkrc
sltxpkg/data/recipes/__init__.py
sltxpkg/data/recipes/compress-latexmk.recipe
sltxpkg/data/recipes/default-latexmk.recipe
sltxpkg/data/recipes/default-lua-latexmk.recipe
sltxpkg/data/recipes/default-lualatex.recipe
sltxpkg/data/recipes/image-noprint-pdflatex.recipe
sltxpkg/data/recipes/image-pdflatex.recipe
sltxpkg/lithie/__init__.py
sltxpkg/lithie/commands.py
sltxpkg/lithie/docker_mg.py
sltxpkg/lithie/analyze/__init__.py
sltxpkg/lithie/analyze/analyzer.py
sltxpkg/lithie/compile/__init__.py
sltxpkg/lithie/compile/cooker.py
sltxpkg/lithie/compile/latexmk_mos.py
sltxpkg/lithie/compile/tools.py
sltxpkg/lithie/compile/cooking/__init__.py
sltxpkg/lithie/compile/cooking/recipe.py
sltxpkg/lithie/compile/cooking/recipe_exceptions.py
sltx-0.1.73.dist-info/LICENSE
sltx-0.1.73.dist-info/METADATA
sltx-0.1.73.dist-info/WHEEL
sltx-0.1.73.dist-info/top_level.txt
sltx-0.1.73.dist-info/RECORD
