Metadata-Version: 2.1
Name: sltx
Version: 0.1.73
Summary: sltx-utility
Home-page: https://github.com/EagleoutIce/sltx
Author: Florian Sihler
Author-email: florian.sihler@uni-ulm.de
Classifier: Programming Language :: Python :: 3
Classifier: License :: OSI Approved :: MIT License
Classifier: Operating System :: OS Independent
Classifier: Intended Audience :: Developers
Classifier: Environment :: Console
Requires-Python: >=3.5
License-File: LICENSE
Requires-Dist: PyYAML
Requires-Dist: docker
Requires-Dist: importlib-resources
Requires-Dist: six
